{
  "title": "Gateway API Lab 1/3 — The Baseline: ingress-nginx",
  "description": "Deploy a bookstore API and expose it with ingress-nginx. Understand the classic Ingress model before migrating to the Kubernetes Gateway API in the next scenario.",
  "difficulty": "Beginner",
  "time": "20",
  "details": {
    "intro": {
      "text": "intro.md",
      "background": "background.sh"
    },
    "steps": [
      {
        "title": "Explore the environment",
        "text": "step1/text.md",
        "verify": "step1/verify.sh"
      },
      {
        "title": "Install ingress-nginx",
        "text": "step2/text.md",
        "verify": "step2/verify.sh"
      },
      {
        "title": "Route traffic with an Ingress resource",
        "text": "step3/text.md",
        "verify": "step3/verify.sh"
      }
    ],
    "finish": {
      "text": "finish.md"
    }
  },
  "backend": {
    "imageid": "kubernetes-kubeadm-1node"
  },
  "assets": {
    "host01": [
      {"file": "manifests/02-ingress-nginx/bookstore-ingress.yaml", "target": "/root/manifests/02-ingress-nginx/"},
      {"file": "manifests/03-gateway-api/gatewayclass.yaml", "target": "/root/manifests/03-gateway-api/"},
      {"file": "manifests/03-gateway-api/gateway-http.yaml", "target": "/root/manifests/03-gateway-api/"},
      {"file": "manifests/03-gateway-api/gateway-https.yaml", "target": "/root/manifests/03-gateway-api/"},
      {"file": "manifests/04-httproutes/basic-route.yaml", "target": "/root/manifests/04-httproutes/"},
      {"file": "manifests/04-httproutes/header-based-route.yaml", "target": "/root/manifests/04-httproutes/"},
      {"file": "manifests/05-advanced/canary-route.yaml", "target": "/root/manifests/05-advanced/"},
      {"file": "manifests/06-traefik-middlewares/httproute-with-middleware.yaml", "target": "/root/manifests/06-traefik-middlewares/"}
    ]
  }
}
